[{"title":"teste","grid_image":"http://i.imgbox.com/PDLgawFY.jpg","full_image":"http://i.imgbox.com/PDLgawFY.jpg"},{"title":"teste","grid_image":"http://i.imgbox.com/PDLgawFY.jpg","full_image":"http://i.imgbox.com/PDLgawFY.jpg"},{"title":"teste","grid_image":"http://i.imgbox.com/PDLgawFY.jpg","full_image":"http://i.imgbox.com/PDLgawFY.jpg"},{"title":"teste","grid_image":"http://i.imgbox.com/PDLgawFY.jpg","full_image":"http://i.imgbox.com/PDLgawFY.jpg"},{"title":"teste","grid_image":"http://i.imgbox.com/PDLgawFY.jpg","full_image":"http://i.imgbox.com/PDLgawFY.jpg"},{"title":"teste","grid_image":"http://i.imgbox.com/PDLgawFY.jpg","full_image":"http://i.imgbox.com/PDLgawFY.jpg"},{"title":"teste","grid_image":"http://i.imgbox.com/PDLgawFY.jpg","full_image":"http://i.imgbox.com/PDLgawFY.jpg"},{"title":"teste","grid_image":"http://i.imgbox.com/PDLgawFY.jpg","full_image":"http://i.imgbox.com/PDLgawFY.jpg"},{"title":"teste","grid_image":"http://i.imgbox.com/PDLgawFY.jpg","full_image":"http://i.imgbox.com/PDLgawFY.jpg"},{"title":"teste","grid_image":"http://i.imgbox.com/PDLgawFY.jpg","full_image":"http://i.imgbox.com/PDLgawFY.jpg"},{"title":"teste","grid_image":"http://i.imgbox.com/PDLgawFY.jpg","full_image":"http://i.imgbox.com/PDLgawFY.jpg"},{"title":"teste","grid_image":"http://i.imgbox.com/PDLgawFY.jpg","full_image":"http://i.imgbox.com/PDLgawFY.jpg"},{"title":"teste","grid_image":"http://i.imgbox.com/PDLgawFY.jpg","full_image":"http://i.imgbox.com/PDLgawFY.jpg"},{"title":"teste","grid_image":"http://i.imgbox.com/PDLgawFY.jpg","full_image":"http://i.imgbox.com/PDLgawFY.jpg"},{"title":"teste","grid_image":"http://i.imgbox.com/PDLgawFY.jpg","full_image":"http://i.imgbox.com/PDLgawFY.jpg"},{"title":"teste","grid_image":"http://i.imgbox.com/PDLgawFY.jpg","full_image":"http://i.imgbox.com/PDLgawFY.jpg"},{"title":"teste","grid_image":"http://i.imgbox.com/PDLgawFY.jpg","full_image":"http://i.imgbox.com/PDLgawFY.jpg"},{"title":"teste","grid_image":"http://i.imgbox.com/PDLgawFY.jpg","full_image":"http://i.imgbox.com/PDLgawFY.jpg"},{"title":"teste","grid_image":"http://i.imgbox.com/PDLgawFY.jpg","full_image":"http://i.imgbox.com/PDLgawFY.jpg"},{"title":"teste","grid_image":"http://i.imgbox.com/PDLgawFY.jpg","full_image":"http://i.imgbox.com/PDLgawFY.jpg"},{"title":"teste","grid_image":"http://i.imgbox.com/PDLgawFY.jpg","full_image":"http://i.imgbox.com/PDLgawFY.jpg"},{"title":"teste","grid_image":"http://i.imgbox.com/PDLgawFY.jpg","full_image":"http://i.imgbox.com/PDLgawFY.jpg"},{"title":"teste","grid_image":"http://i.imgbox.com/PDLgawFY.jpg","full_image":"http://i.imgbox.com/PDLgawFY.jpg"},{"title":"teste","grid_image":"http://i.imgbox.com/PDLgawFY.jpg","full_image":"http://i.imgbox.com/PDLgawFY.jpg"},{"title":"teste","grid_image":"http://i.imgbox.com/PDLgawFY.jpg","full_image":"http://i.imgbox.com/PDLgawFY.jpg"},{"title":"teste","grid_image":"http://i.imgbox.com/PDLgawFY.jpg","full_image":"http://i.imgbox.com/PDLgawFY.jpg"},{"title":"teste","grid_image":"http://i.imgbox.com/PDLgawFY.jpg","full_image":"http://i.imgbox.com/PDLgawFY.jpg"},{"title":"teste","grid_image":"http://i.imgbox.com/PDLgawFY.jpg","full_image":"http://i.imgbox.com/PDLgawFY.jpg"}]
